sparsely_connected_keras/__init__.py
sparsely_connected_keras/sparse_layer.py
sparsely_connected_keras-1.0.0.dist-info/LICENSE
sparsely_connected_keras-1.0.0.dist-info/METADATA
sparsely_connected_keras-1.0.0.dist-info/WHEEL
sparsely_connected_keras-1.0.0.dist-info/top_level.txt
sparsely_connected_keras-1.0.0.dist-info/RECORD
